<?xml version="1.0" encoding="utf-8" ?>
<dwsync>
<file name="lang2.php" local="128896209900000000" remote="0" testing="128896209900000000" />
<file name="md5.js" local="128345220000000000" remote="0" testing="128345220000000000" />
<file name="cssAdmin.css" local="128510244000000000" remote="0" testing="128510244000000000" />
<file name="javascript.lib.js" local="128970328800000000" remote="0" testing="128970328800000000" />
<file name="varAlert.vn.unicode.js" local="128705194200000000" remote="0" testing="128705194200000000" />
<file name="smtp.php" local="128970328840000000" remote="0" testing="128970328840000000" />
<file name="getmxrr.php" local="128970328780000000" remote="0" testing="128970328780000000" />
<file name="func.lib.php" local="128970328760000000" remote="0" testing="128970328760000000" />
</dwsync>